filehandling/__init__.py
file_handling-1.0.1.dist-info/LICENSE
file_handling-1.0.1.dist-info/METADATA
file_handling-1.0.1.dist-info/WHEEL
file_handling-1.0.1.dist-info/top_level.txt
file_handling-1.0.1.dist-info/RECORD
