Metadata-Version: 2.1
Name: file-handling
Version: 1.0.1
Summary: file_handling
Home-page: https://github.com/Sotaneum/file-handling
Author: sotaneum
Author-email: gnyontu39@gmail.com
License: UNKNOWN
Platform: UNKNOWN
Classifier: Programming Language :: Python :: 3
Classifier: License :: OSI Approved :: MIT License
Classifier: Operating System :: OS Independent
Requires-Python: >=3.6
License-File: LICENSE
Requires-Dist: deep-folder (==1.*)
